[
    {
        "Name": "Cashmere wool down jacket",
        "Price": "£ 2,500"
    },
    {
        "Name": "Re-Nylon cropped hooded down jacket",
        "Price": "£ 2,200"
    },
    {
        "Name": "Re-Nylon hooded down jacket",
        "Price": "£ 2,650"
    },
    {
        "Name": "Light Re-Nylon trench coat",
        "Price": "£ 2,750"
    },
    {
        "Name": "Re-Nylon cropped jacket",
        "Price": "£ 2,300"
    },
    {
        "Name": "Light Re-Nylon blouson jacket",
        "Price": "£ 2,800"
    },
    {
        "Name": "Re-Nylon Gabardine hooded down coat",
        "Price": "£ 2,200"
    },
    {
        "Name": "Re-Nylon cropped down jacket",
        "Price": "£ 1,850"
    },
    {
        "Name": "Re-Nylon cropped down vest",
        "Price": "£ 1,600"
    },
    {
        "Name": "Light Re-Nylon puffer jacket",
        "Price": "£ 1,850"
    },
    {
        "Name": "Light Re-Nylon down jacket",
        "Price": "£ 1,950"
    },
    {
        "Name": "Re-Nylon cropped convertible down jacket",
        "Price": "£ 1,650"
    },
    {
        "Name": "Re-Nylon cropped convertible down jacket",
        "Price": "£ 1,650"
    },
    {
        "Name": "Re-Nylon hooded down jacket",
        "Price": "£ 1,850"
    },
    {
        "Name": "Re-Nylon hooded down jacket",
        "Price": "£ 1,850"
    },
    {
        "Name": "Re-Nylon convertible down jacket",
        "Price": "£ 1,850"
    },
    {
        "Name": "Re-Nylon convertible cropped down jacket",
        "Price": "£ 1,690"
    },
    {
        "Name": "Re-Nylon convertible cropped down jacket",
        "Price": "£ 1,690"
    },
    {
        "Name": "Ciré cropped down jacket",
        "Price": "£ 1,950"
    },
    {
        "Name": "Re-Nylon cropped hooded down jacket",
        "Price": "£ 1,850"
    },
    {
        "Name": "Re-Nylon down jacket",
        "Price": "£ 2,150"
    },
    {
        "Name": "Re-Nylon down coat",
        "Price": "£ 2,900"
    },
    {
        "Name": "Hooded Re-Nylon down coat",
        "Price": "£ 2,900"
    },
    {
        "Name": "Re-Nylon down jacket",
        "Price": "£ 2,400"
    }
]