[
    {
        "Name": "Metallic leather loafers",
        "Price": "£ 980"
    },
    {
        "Name": "Metallic leather loafers",
        "Price": "£ 980"
    },
    {
        "Name": "Chocolate brushed leather loafers",
        "Price": "£ 890"
    },
    {
        "Name": "Chocolate high-heeled brushed leather loafers",
        "Price": "£ 930"
    },
    {
        "Name": "Heeled brushed leather lace-ups",
        "Price": "£ 930"
    },
    {
        "Name": "Brushed-leather Mary Jane T-strap shoes",
        "Price": "£ 880"
    },
    {
        "Name": "Monolith brushed leather lace-up shoes",
        "Price": "£ 920"
    },
    {
        "Name": "Brushed leather Monolith loafers",
        "Price": "£ 920"
    },
    {
        "Name": "Patent leather ballerinas",
        "Price": "£ 830"
    },
    {
        "Name": "Metallic leather ballerinas",
        "Price": "£ 870"
    },
    {
        "Name": "Metallic leather ballerinas",
        "Price": "£ 870"
    },
    {
        "Name": "Nappa leather ballerinas",
        "Price": "£ 720"
    },
    {
        "Name": "Nappa leather ballerinas",
        "Price": "£ 720"
    },
    {
        "Name": "Patent leather loafers",
        "Price": "£ 890"
    },
    {
        "Name": "Brushed leather loafers",
        "Price": "£ 890"
    },
    {
        "Name": "Brushed-leather derby shoes",
        "Price": "£ 860"
    },
    {
        "Name": "Leather booties",
        "Price": "£ 1,090"
    },
    {
        "Name": "Leather boots",
        "Price": "£ 1,440"
    },
    {
        "Name": "Brushed leather and nylon boots",
        "Price": "£ 1,240"
    },
    {
        "Name": "Brushed leather and Re-Nylon boots",
        "Price": "£ 1,440"
    },
    {
        "Name": "Heeled brushed leather booties",
        "Price": "£ 1,040"
    },
    {
        "Name": "Brushed-leather and Re-Nylon boots",
        "Price": "£ 1,080"
    },
    {
        "Name": "Brushed leather and nylon booties",
        "Price": "£ 1,050"
    },
    {
        "Name": "Brushed leather and nylon laced booties",
        "Price": "£ 980"
    }
]